MANIFEST.in
account_chart_skr03.xml
account_chart_skr04.xml
account_chart_template_skr03.xml
account_chart_template_skr04.xml
account_tax_fiscal_position_skr03.xml
account_tax_fiscal_position_skr04.xml
account_tax_skr03.xml
account_tax_skr04.xml
account_types_skr03.xml
account_types_skr04.xml
l10n_de_wizard.xml
setup.py
./__init__.py
./__openerp__.py
i18n/ar.po
i18n/ar_AR.po
i18n/be_BE.po
i18n/bg.po
i18n/bg_BG.po
i18n/bs.po
i18n/bs_BS.po
i18n/ca.po
i18n/ca_ES.po
i18n/cs.po
i18n/cs_CZ.po
i18n/da.po
i18n/de.po
i18n/es.po
i18n/es_AR.po
i18n/es_CR.po
i18n/es_ES.po
i18n/es_MX.po
i18n/es_PY.po
i18n/es_VE.po
i18n/et.po
i18n/et_EE.po
i18n/fi_FI.po
i18n/fr.po
i18n/fr_FR.po
i18n/gl.po
i18n/hr.po
i18n/hr_HR.po
i18n/hu.po
i18n/hu_HU.po
i18n/id.po
i18n/id_ID.po
i18n/it.po
i18n/it_IT.po
i18n/ko.po
i18n/ko_KO.po
i18n/l10n_de.pot
i18n/lt.po
i18n/lt_LT.po
i18n/nb.po
i18n/nl.po
i18n/nl_BE.po
i18n/nl_NL.po
i18n/pl.po
i18n/pl_PL.po
i18n/pt.po
i18n/pt_BR.po
i18n/pt_PT.po
i18n/ro.po
i18n/ro_RO.po
i18n/ru.po
i18n/ru_RU.po
i18n/sl.po
i18n/sl_SL.po
i18n/sq_AL.po
i18n/sr@latin.po
i18n/sv.po
i18n/sv_SE.po
i18n/tr.po
i18n/tr_TR.po
i18n/uk_UA.po
i18n/vi.po
i18n/vi_VN.po
i18n/zh_CN.po
i18n/zh_TW.po
i18n/znd_ZND.po
images/config_chart_l10n_de.jpeg
images/l10n_de_chart.jpeg
openerp_l10n_de.egg-info/PKG-INFO
openerp_l10n_de.egg-info/SOURCES.txt
openerp_l10n_de.egg-info/dependency_links.txt
openerp_l10n_de.egg-info/requires.txt
openerp_l10n_de.egg-info/top_level.txt
static/src/img/icon.png