Metadata-Version: 1.1
Name: openerp-l10n-de
Version: 7.0.355
Summary: Deutschland - Accounting
Home-page: http://www.openbig.org
Author: openbig.org
Author-email: TODO
License: AGPL-3
Platform: UNKNOWN
Classifier: Development Status :: 5 - Production/Stable
Classifier: Environment :: Plugins
Classifier: Intended Audience :: Developers
Classifier: License :: OSI Approved :: GNU Affero General Public License v3
Classifier: Natural Language :: English
Classifier: Programming Language :: Python :: 2.7
Classifier: Programming Language :: Python :: Implementation :: CPython
